unfolding/DDB_unfolder.py
unfolding/__init__.py
unfolding/phonon_unfolder.py
unfolding/phonopy_unfolder.py
unfolding/plotphon.py
unfolding/unfolder.py
unfolding-0.1.dist-info/licenses/LICENSE
unfolding-0.1.dist-info/METADATA
unfolding-0.1.dist-info/WHEEL
unfolding-0.1.dist-info/top_level.txt
unfolding-0.1.dist-info/RECORD
